automatix/__init__.py
automatix_cmd-2.5.99.dist-info/METADATA
automatix_cmd-2.5.99.dist-info/WHEEL
automatix_cmd-2.5.99.dist-info/entry_points.txt
automatix_cmd-2.5.99.dist-info/top_level.txt
automatix_cmd-2.5.99.dist-info/RECORD
